cau_auth/__init__.py
cau_auth/cau.py
cau_auth/src/__init__.py
cau_auth/src/core/__init__.py
cau_auth/src/core/check_status.py
cau_auth/src/core/create_config.py
cau_auth/src/core/login.py
cau_auth/src/core/logout.py
cau_auth/src/core/real_auth_ip.py
cau_auth/src/helper/__init__.py
cau_auth/src/helper/init_helper.py
cau_auth/src/utils/__init__.py
cau_auth/src/utils/args_parser.py
cau_auth/src/utils/get_host_ip.py
cau_auth/src/utils/sys_user.py
cau_auth/statics/__init__.py
cau_auth/statics/argparse_description.txt
cau_auth/statics/config_example.txt
cau-0.0.3.dist-info/METADATA
cau-0.0.3.dist-info/WHEEL
cau-0.0.3.dist-info/entry_points.txt
cau-0.0.3.dist-info/top_level.txt
cau-0.0.3.dist-info/RECORD
