Metadata-Version: 2.1
Name: cau
Version: 0.0.3
Summary: 通过命令行进行中国农业大学的校园网认证
Home-page: https://github.com/NingYuanLin/cau_auth
Author: nyl
Author-email: c2605759123@163.com
License: UNKNOWN
Platform: UNKNOWN
Requires-Dist: requests
